odoo/addons/stock_picking_group_by_partner_by_carrier_sale_line_position/README.rst
odoo/addons/stock_picking_group_by_partner_by_carrier_sale_line_position/__init__.py
odoo/addons/stock_picking_group_by_partner_by_carrier_sale_line_position/__manifest__.py
odoo/addons/stock_picking_group_by_partner_by_carrier_sale_line_position/i18n/it.po
odoo/addons/stock_picking_group_by_partner_by_carrier_sale_line_position/i18n/stock_picking_group_by_partner_by_carrier_sale_line_position.pot
odoo/addons/stock_picking_group_by_partner_by_carrier_sale_line_position/models/__init__.py
odoo/addons/stock_picking_group_by_partner_by_carrier_sale_line_position/models/stock_picking.py
odoo/addons/stock_picking_group_by_partner_by_carrier_sale_line_position/readme/CONTRIBUTORS.md
odoo/addons/stock_picking_group_by_partner_by_carrier_sale_line_position/readme/CREDITS.md
odoo/addons/stock_picking_group_by_partner_by_carrier_sale_line_position/readme/DESCRIPTION.md
odoo/addons/stock_picking_group_by_partner_by_carrier_sale_line_position/report/report_deliveryslip.xml
odoo/addons/stock_picking_group_by_partner_by_carrier_sale_line_position/static/description/icon.png
odoo/addons/stock_picking_group_by_partner_by_carrier_sale_line_position/static/description/index.html
odoo/addons/stock_picking_group_by_partner_by_carrier_sale_line_position/tests/__init__.py
odoo/addons/stock_picking_group_by_partner_by_carrier_sale_line_position/tests/test_stock_picking.py
odoo_addon_stock_picking_group_by_partner_by_carrier_sale_line_position-18.0.1.0.0.3.dist-info/METADATA
odoo_addon_stock_picking_group_by_partner_by_carrier_sale_line_position-18.0.1.0.0.3.dist-info/WHEEL
odoo_addon_stock_picking_group_by_partner_by_carrier_sale_line_position-18.0.1.0.0.3.dist-info/top_level.txt
odoo_addon_stock_picking_group_by_partner_by_carrier_sale_line_position-18.0.1.0.0.3.dist-info/RECORD
