Metadata-Version: 2.1
Name: odoo-addon-stock_picking_group_by_partner_by_carrier_sale_line_position
Version: 18.0.1.0.0.3
Requires-Python: >=3.10
Requires-Dist: odoo-addon-delivery_line_sale_line_position==18.0.*
Requires-Dist: odoo-addon-stock_picking_group_by_partner_by_carrier==18.0.*
Requires-Dist: odoo==18.0.*
Summary: Glue module for sale position and delivery report grouped
Home-page: https://github.com/OCA/stock-logistics-reporting
License: AGPL-3
Author: Camptocamp, Odoo Community Association (OCA)
Author-email: support@odoo-community.org
Classifier: Programming Language :: Python
Classifier: Framework :: Odoo
Classifier: Framework :: Odoo :: 18.0
Classifier: License :: OSI Approved :: GNU Affero General Public License v3
